setup.py
bzz/__init__.py
bzz/auth.py
bzz/core.py
bzz/mock.py
bzz/model.py
bzz/signals.py
bzz/utils.py
bzz/version.py
bzz.egg-info/PKG-INFO
bzz.egg-info/SOURCES.txt
bzz.egg-info/dependency_links.txt
bzz.egg-info/entry_points.txt
bzz.egg-info/requires.txt
bzz.egg-info/top_level.txt
bzz/providers/__init__.py
bzz/providers/google.py
bzz/providers/mock.py
bzz/providers/mongoengine_provider.py
tests/__init__.py
tests/base.py
tests/fixtures.py
tests/test_auth_hive.py
tests/test_model_hive_e2e.py
tests/test_models.py
tests/mock_hive/__init__.py
tests/mock_hive/test_mock_hive.py
tests/models/__init__.py
tests/models/mongoengine_models.py
tests/providers/__init__.py
tests/providers/test_mongoengine_provider.py