Metadata-Version: 1.1
Name: bzz
Version: 0.8.0
Summary: bzz is a Rest API framework for working bees.
Home-page: https://github.com/heynemann/bzz
Author: Bernardo Heynemann
Author-email: heynemann@gmail.com
License: MIT
Keywords: api rest tornado hal
Platform: UNKNOWN
Classifier: Development Status :: 4 - Beta
Classifier: Intended Audience :: Developers
Classifier: License :: OSI Approved :: MIT License
Classifier: Natural Language :: English
Classifier: Operating System :: Unix
Classifier: Programming Language :: Python :: 2.7
Classifier: Programming Language :: Python :: 3.4
Classifier: Programming Language :: Python :: Implementation :: PyPy
Classifier: Operating System :: OS Independent
